MANIFEST.in
README.md
pyproject.toml
setup.py
amuse_bhtree.egg-info/PKG-INFO
amuse_bhtree.egg-info/SOURCES.txt
amuse_bhtree.egg-info/dependency_links.txt
amuse_bhtree.egg-info/requires.txt
amuse_bhtree.egg-info/top_level.txt
src/amuse/community/bhtree/Makefile
src/amuse/community/bhtree/__init__.py
src/amuse/community/bhtree/_version.py
src/amuse/community/bhtree/interface.cc
src/amuse/community/bhtree/interface.h
src/amuse/community/bhtree/interface.py
src/amuse/community/bhtree/src/BHTC.C
src/amuse/community/bhtree/src/BHTC.h
src/amuse/community/bhtree/src/BHtree.C
src/amuse/community/bhtree/src/BHtree.h
src/amuse/community/bhtree/src/COPYRIGHT
src/amuse/community/bhtree/src/Makefile
src/amuse/community/bhtree/src/README
src/amuse/community/bhtree/src/gravity.C
src/amuse/community/bhtree/src/nbody.C
src/amuse/community/bhtree/src/nbody_particle.h
src/amuse/community/bhtree/src/pgetopt.C
src/amuse/community/bhtree/src/second.c
src/amuse/community/bhtree/src/stdinc.h
src/amuse/community/bhtree/src/vec.h
support/__init__.py
support/classifiers.py
support/config.py
support/generate_main.py
support/getsp.class
support/getsp.java
support/misc.py
support/setup_codes.py
support/version.py